lyricsipsum/__init__.py
lyricsipsum/__main__.py
lyricsipsum-1.1.3.dist-info/METADATA
lyricsipsum-1.1.3.dist-info/WHEEL
lyricsipsum-1.1.3.dist-info/entry_points.txt
lyricsipsum-1.1.3.dist-info/licenses/LICENSE
lyricsipsum-1.1.3.dist-info/RECORD
