Metadata-Version: 2.4
Name: lyricsipsum
Version: 1.1.3
Summary: Generates Lorem Ipsum text using song lyrics
License-Expression: MIT
License-File: LICENSE
Keywords: lorem,ipsum,text,generator,lyrics,utility,command-line,cli
Author: Steve Scholnick
Author-email: scholnicks@gmail.com
Requires-Python: >=3.14
Classifier: Development Status :: 5 - Production/Stable
Classifier: Intended Audience :: Developers
Classifier: Programming Language :: Python :: 3.14
Classifier: License :: OSI Approved :: MIT License
Classifier: Topic :: Utilities
Requires-Dist: docopt-ng (>=0.9.0,<0.10.0)
Requires-Dist: lyricsgenius (>=3.7.2,<4.0.0)
Project-URL: Homepage, https://pypi.org/project/lyricsipsum/
Project-URL: Repository, https://github.com/scholnicks/lyricsipsum/
Project-URL: issues, https://github.com/scholnicks/lyricsipsum/issues
